version.py
LICENSE
ballast/__init__.py
ballast/core.py
ballast/exception.py
ballast/ping.py
ballast/rule.py
ballast/service.py
ballast/util.py
ballast/discovery/__init__.py
ballast/discovery/consul.py
ballast/discovery/ns.py
ballast/discovery/static.py
ballast-0.4.0.dist-info/top_level.txt
ballast-0.4.0.dist-info/METADATA
ballast-0.4.0.dist-info/DESCRIPTION.rst
ballast-0.4.0.dist-info/metadata.json
ballast-0.4.0.dist-info/WHEEL
ballast-0.4.0.dist-info/RECORD
