Metadata-Version: 2.0
Name: ballast
Version: 0.4.0
Summary: Ballast client-side load-balancing framework
Home-page: https://github.com/thomasstreet/ballast
Author: Justin Smith
Author-email: smith.justin.c@gmail.com
License: Apache License 2.0
Keywords: alpha development load-balancing
Platform: UNKNOWN
Classifier: Development Status :: 3 - Alpha
Classifier: Intended Audience :: Developers
Classifier: Topic :: Software Development :: Libraries :: Python Modules
Classifier: License :: OSI Approved :: Apache Software License
Classifier: Programming Language :: Python :: 2
Classifier: Programming Language :: Python :: 2.7
Classifier: Programming Language :: Python :: 3
Classifier: Programming Language :: Python :: 3.3
Classifier: Programming Language :: Python :: 3.4
Classifier: Programming Language :: Python :: 3.5
Classifier: Programming Language :: Python :: 3.6
Classifier: Programming Language :: Python :: Implementation :: CPython
Classifier: Programming Language :: Python :: Implementation :: PyPy
Requires-Dist: requests
Requires-Dist: future
Provides-Extra: all
Requires-Dist: dnspython; extra == 'all'
Requires-Dist: gevent; extra == 'all'
Provides-Extra: dns
Requires-Dist: dnspython; extra == 'dns'
Provides-Extra: gevent
Requires-Dist: gevent; extra == 'gevent'
